closive/Closive.ipynb
closive/LICENSE
closive/__init__.py
closive/_importer.py
closive/closures.py
closive/commutators.py
closive/jit.py
closive/monads.py
closive/rtypes.py
closive/setup.py
closive-0.0.0.dev26.dist-info/METADATA
closive-0.0.0.dev26.dist-info/WHEEL
closive-0.0.0.dev26.dist-info/RECORD
