Metadata-Version: 2.4
Name: closive
Version: 0.0.0.dev26
Summary: Abstractions for callback-heavy control flows.
Author-email: kosmolebryce <k.lebryce@pm.me>
Requires-Python: >=3.11.0
Requires-Dist: ipykernel>=6.29.5
Requires-Dist: jupyterlab-myst>=2.4.2
Requires-Dist: mystmd>=1.3.26
Requires-Dist: returns>=0.25.0
